LICENSE
MANIFEST.in
README.rst
setup.py
fabric_bolt/__init__.py
fabric_bolt/fabfile.py
fabric_bolt/manage.py
fabric_bolt/wsgi.py
fabric_bolt.egg-info/PKG-INFO
fabric_bolt.egg-info/SOURCES.txt
fabric_bolt.egg-info/dependency_links.txt
fabric_bolt.egg-info/entry_points.txt
fabric_bolt.egg-info/not-zip-safe
fabric_bolt.egg-info/pbr.json
fabric_bolt.egg-info/requires.txt
fabric_bolt.egg-info/top_level.txt
fabric_bolt/accounts/__init__.py
fabric_bolt/accounts/admin.py
fabric_bolt/accounts/forms.py
fabric_bolt/accounts/managers.py
fabric_bolt/accounts/models.py
fabric_bolt/accounts/tables.py
fabric_bolt/accounts/urls.py
fabric_bolt/accounts/views.py
fabric_bolt/accounts/migrations/0001_initial.py
fabric_bolt/accounts/migrations/0002_auto_20140811_1921.py
fabric_bolt/accounts/migrations/0003_auto_20140905_2212.py
fabric_bolt/accounts/migrations/0004_auto_20150813_0148.py
fabric_bolt/accounts/migrations/__init__.py
fabric_bolt/accounts/templates/accounts/deployuser_change.html
fabric_bolt/accounts/templates/accounts/deployuser_confirm_delete.html
fabric_bolt/accounts/templates/accounts/deployuser_create.html
fabric_bolt/accounts/templates/accounts/deployuser_detail.html
fabric_bolt/accounts/templates/accounts/password_change.html
fabric_bolt/accounts/templates/accounts/password_create.html
fabric_bolt/accounts/templates/accounts/permissions.html
fabric_bolt/accounts/templates/accounts/user_list.html
fabric_bolt/accounts/templates/accounts/welcome_email.html
fabric_bolt/accounts/tests/__init__.py
fabric_bolt/accounts/tests/test_general.py
fabric_bolt/accounts/tests/test_views.py
fabric_bolt/core/__init__.py
fabric_bolt/core/context_processors.py
fabric_bolt/core/themes.py
fabric_bolt/core/urls.py
fabric_bolt/core/views.py
fabric_bolt/core/wsgi.py
fabric_bolt/core/fixtures/.gitdirectory
fabric_bolt/core/mixins/__init__.py
fabric_bolt/core/mixins/models.py
fabric_bolt/core/mixins/tables.py
fabric_bolt/core/mixins/views.py
fabric_bolt/core/settings/__init__.py
fabric_bolt/core/settings/base.py
fabric_bolt/core/settings/develop.py
fabric_bolt/core/settings/local.py
fabric_bolt/core/settings/production.py
fabric_bolt/core/settings/staging.py
fabric_bolt/core/settings/test.py
fabric_bolt/core/static/.gitdirectory
