Metadata-Version: 1.1
Name: fabric-bolt
Version: 0.1
Summary: A web interface to fabric deployments.
Home-page: https://github.com/fabric-bolt/fabric-bolt
Author: Dan Dietz, Nathaniel Pardington, Jared Proffitt
Author-email: UNKNOWN
License: MIT
Platform: UNKNOWN
Classifier: Framework :: Django
Classifier: Programming Language :: Python
